{"nodes": [{"id": "d_projects_edithub_flutter_app_lib_theme_dart", "label": "theme.dart", "file_type": "code", "source_file": "lib/theme.dart", "source_location": null}, {"id": "d_projects_edithub_flutter_app_lib_theme_appcolors", "label": "AppColors", "file_type": "code", "source_file": "lib/theme.dart", "source_location": null}, {"id": "d_projects_edithub_flutter_app_lib_theme_bg", "label": "bg", "file_type": "code", "source_file": "lib/theme.dart", "source_location": null}, {"id": "static_const", "label": "static const", "file_type": "code", "source_file": null, "source_location": null}, {"id": "d_projects_edithub_flutter_app_lib_theme_card", "label": "card", "file_type": "code", "source_file": "lib/theme.dart", "source_location": null}, {"id": "d_projects_edithub_flutter_app_lib_theme_card2", "label": "card2", "file_type": "code", "source_file": "lib/theme.dart", "source_location": null}, {"id": "d_projects_edithub_flutter_app_lib_theme_txt", "label": "txt", "file_type": "code", "source_file": "lib/theme.dart", "source_location": null}, {"id": "d_projects_edithub_flutter_app_lib_theme_dim", "label": "dim", "file_type": "code", "source_file": "lib/theme.dart", "source_location": null}, {"id": "d_projects_edithub_flutter_app_lib_theme_accent", "label": "accent", "file_type": "code", "source_file": "lib/theme.dart", "source_location": null}, {"id": "d_projects_edithub_flutter_app_lib_theme_accenthover", "label": "accentHover", "file_type": "code", "source_file": "lib/theme.dart", "source_location": null}, {"id": "d_projects_edithub_flutter_app_lib_theme_sep", "label": "sep", "file_type": "code", "source_file": "lib/theme.dart", "source_location": null}, {"id": "d_projects_edithub_flutter_app_lib_theme_good", "label": "good", "file_type": "code", "source_file": "lib/theme.dart", "source_location": null}, {"id": "d_projects_edithub_flutter_app_lib_theme_bad", "label": "bad", "file_type": "code", "source_file": "lib/theme.dart", "source_location": null}, {"id": "d_projects_edithub_flutter_app_lib_theme_warn", "label": "warn", "file_type": "code", "source_file": "lib/theme.dart", "source_location": null}, {"id": "d_projects_edithub_flutter_app_lib_theme_brand", "label": "brand", "file_type": "code", "source_file": "lib/theme.dart", "source_location": null}, {"id": "d_projects_edithub_flutter_app_lib_theme_radius", "label": "radius", "file_type": "code", "source_file": "lib/theme.dart", "source_location": null}, {"id": "static_const_double", "label": "static const double", "file_type": "code", "source_file": null, "source_location": null}, {"id": "d_projects_edithub_flutter_app_lib_theme_radiussm", "label": "radiusSm", "file_type": "code", "source_file": "lib/theme.dart", "source_location": null}, {"id": "d_projects_edithub_flutter_app_lib_theme_base", "label": "base", "file_type": "code", "source_file": "lib/theme.dart", "source_location": null}, {"id": "d_projects_edithub_flutter_app_lib_theme_buildtheme", "label": "buildTheme", "file_type": "code", "source_file": "lib/theme.dart", "source_location": null}, {"id": "d_projects_edithub_flutter_app_lib_theme_copywith", "label": "copyWith", "file_type": "code", "source_file": "lib/theme.dart", "source_location": null}, {"id": "package_flutter_material_dart", "label": "package:flutter/material.dart", "file_type": "code", "source_file": null, "source_location": null}, {"id": "package_google_fonts_google_fonts_dart", "label": "package:google_fonts/google_fonts.dart", "file_type": "code", "source_file": null, "source_location": null}], "edges": [{"source": "d_projects_edithub_flutter_app_lib_theme_dart", "target": "d_projects_edithub_flutter_app_lib_theme_appcolors", "relation": "defines", "confidence": "EXTRACTED", "confidence_score": 1.0, "source_file": "lib/theme.dart", "source_location": null, "weight": 1.0}, {"source": "d_projects_edithub_flutter_app_lib_theme_dart", "target": "d_projects_edithub_flutter_app_lib_theme_bg", "relation": "defines", "confidence": "EXTRACTED", "confidence_score": 1.0, "source_file": "lib/theme.dart", "source_location": null, "weight": 1.0}, {"source": "d_projects_edithub_flutter_app_lib_theme_dart", "target": "static_const", "relation": "references", "confidence": "EXTRACTED", "confidence_score": 1.0, "source_file": "lib/theme.dart", "source_location": null, "weight": 1.0, "context": "variable_type"}, {"source": "d_projects_edithub_flutter_app_lib_theme_dart", "target": "d_projects_edithub_flutter_app_lib_theme_card", "relation": "defines", "confidence": "EXTRACTED", "confidence_score": 1.0, "source_file": "lib/theme.dart", "source_location": null, "weight": 1.0}, {"source": "d_projects_edithub_flutter_app_lib_theme_dart", "target": "static_const", "relation": "references", "confidence": "EXTRACTED", "confidence_score": 1.0, "source_file": "lib/theme.dart", "source_location": null, "weight": 1.0, "context": "variable_type"}, {"source": "d_projects_edithub_flutter_app_lib_theme_dart", "target": "d_projects_edithub_flutter_app_lib_theme_card2", "relation": "defines", "confidence": "EXTRACTED", "confidence_score": 1.0, "source_file": "lib/theme.dart", "source_location": null, "weight": 1.0}, {"source": "d_projects_edithub_flutter_app_lib_theme_dart", "target": "static_const", "relation": "references", "confidence": "EXTRACTED", "confidence_score": 1.0, "source_file": "lib/theme.dart", "source_location": null, "weight": 1.0, "context": "variable_type"}, {"source": "d_projects_edithub_flutter_app_lib_theme_dart", "target": "d_projects_edithub_flutter_app_lib_theme_txt", "relation": "defines", "confidence": "EXTRACTED", "confidence_score": 1.0, "source_file": "lib/theme.dart", "source_location": null, "weight": 1.0}, {"source": "d_projects_edithub_flutter_app_lib_theme_dart", "target": "static_const", "relation": "references", "confidence": "EXTRACTED", "confidence_score": 1.0, "source_file": "lib/theme.dart", "source_location": null, "weight": 1.0, "context": "variable_type"}, {"source": "d_projects_edithub_flutter_app_lib_theme_dart", "target": "d_projects_edithub_flutter_app_lib_theme_dim", "relation": "defines", "confidence": "EXTRACTED", "confidence_score": 1.0, "source_file": "lib/theme.dart", "source_location": null, "weight": 1.0}, {"source": "d_projects_edithub_flutter_app_lib_theme_dart", "target": "static_const", "relation": "references", "confidence": "EXTRACTED", "confidence_score": 1.0, "source_file": "lib/theme.dart", "source_location": null, "weight": 1.0, "context": "variable_type"}, {"source": "d_projects_edithub_flutter_app_lib_theme_dart", "target": "d_projects_edithub_flutter_app_lib_theme_accent", "relation": "defines", "confidence": "EXTRACTED", "confidence_score": 1.0, "source_file": "lib/theme.dart", "source_location": null, "weight": 1.0}, {"source": "d_projects_edithub_flutter_app_lib_theme_dart", "target": "static_const", "relation": "references", "confidence": "EXTRACTED", "confidence_score": 1.0, "source_file": "lib/theme.dart", "source_location": null, "weight": 1.0, "context": "variable_type"}, {"source": "d_projects_edithub_flutter_app_lib_theme_dart", "target": "d_projects_edithub_flutter_app_lib_theme_accenthover", "relation": "defines", "confidence": "EXTRACTED", "confidence_score": 1.0, "source_file": "lib/theme.dart", "source_location": null, "weight": 1.0}, {"source": "d_projects_edithub_flutter_app_lib_theme_dart", "target": "static_const", "relation": "references", "confidence": "EXTRACTED", "confidence_score": 1.0, "source_file": "lib/theme.dart", "source_location": null, "weight": 1.0, "context": "variable_type"}, {"source": "d_projects_edithub_flutter_app_lib_theme_dart", "target": "d_projects_edithub_flutter_app_lib_theme_sep", "relation": "defines", "confidence": "EXTRACTED", "confidence_score": 1.0, "source_file": "lib/theme.dart", "source_location": null, "weight": 1.0}, {"source": "d_projects_edithub_flutter_app_lib_theme_dart", "target": "static_const", "relation": "references", "confidence": "EXTRACTED", "confidence_score": 1.0, "source_file": "lib/theme.dart", "source_location": null, "weight": 1.0, "context": "variable_type"}, {"source": "d_projects_edithub_flutter_app_lib_theme_dart", "target": "d_projects_edithub_flutter_app_lib_theme_good", "relation": "defines", "confidence": "EXTRACTED", "confidence_score": 1.0, "source_file": "lib/theme.dart", "source_location": null, "weight": 1.0}, {"source": "d_projects_edithub_flutter_app_lib_theme_dart", "target": "static_const", "relation": "references", "confidence": "EXTRACTED", "confidence_score": 1.0, "source_file": "lib/theme.dart", "source_location": null, "weight": 1.0, "context": "variable_type"}, {"source": "d_projects_edithub_flutter_app_lib_theme_dart", "target": "d_projects_edithub_flutter_app_lib_theme_bad", "relation": "defines", "confidence": "EXTRACTED", "confidence_score": 1.0, "source_file": "lib/theme.dart", "source_location": null, "weight": 1.0}, {"source": "d_projects_edithub_flutter_app_lib_theme_dart", "target": "static_const", "relation": "references", "confidence": "EXTRACTED", "confidence_score": 1.0, "source_file": "lib/theme.dart", "source_location": null, "weight": 1.0, "context": "variable_type"}, {"source": "d_projects_edithub_flutter_app_lib_theme_dart", "target": "d_projects_edithub_flutter_app_lib_theme_warn", "relation": "defines", "confidence": "EXTRACTED", "confidence_score": 1.0, "source_file": "lib/theme.dart", "source_location": null, "weight": 1.0}, {"source": "d_projects_edithub_flutter_app_lib_theme_dart", "target": "static_const", "relation": "references", "confidence": "EXTRACTED", "confidence_score": 1.0, "source_file": "lib/theme.dart", "source_location": null, "weight": 1.0, "context": "variable_type"}, {"source": "d_projects_edithub_flutter_app_lib_theme_dart", "target": "d_projects_edithub_flutter_app_lib_theme_brand", "relation": "defines", "confidence": "EXTRACTED", "confidence_score": 1.0, "source_file": "lib/theme.dart", "source_location": null, "weight": 1.0}, {"source": "d_projects_edithub_flutter_app_lib_theme_dart", "target": "static_const", "relation": "references", "confidence": "EXTRACTED", "confidence_score": 1.0, "source_file": "lib/theme.dart", "source_location": null, "weight": 1.0, "context": "variable_type"}, {"source": "d_projects_edithub_flutter_app_lib_theme_dart", "target": "d_projects_edithub_flutter_app_lib_theme_radius", "relation": "defines", "confidence": "EXTRACTED", "confidence_score": 1.0, "source_file": "lib/theme.dart", "source_location": null, "weight": 1.0}, {"source": "d_projects_edithub_flutter_app_lib_theme_dart", "target": "static_const_double", "relation": "references", "confidence": "EXTRACTED", "confidence_score": 1.0, "source_file": "lib/theme.dart", "source_location": null, "weight": 1.0, "context": "variable_type"}, {"source": "d_projects_edithub_flutter_app_lib_theme_dart", "target": "d_projects_edithub_flutter_app_lib_theme_radiussm", "relation": "defines", "confidence": "EXTRACTED", "confidence_score": 1.0, "source_file": "lib/theme.dart", "source_location": null, "weight": 1.0}, {"source": "d_projects_edithub_flutter_app_lib_theme_dart", "target": "static_const_double", "relation": "references", "confidence": "EXTRACTED", "confidence_score": 1.0, "source_file": "lib/theme.dart", "source_location": null, "weight": 1.0, "context": "variable_type"}, {"source": "d_projects_edithub_flutter_app_lib_theme_dart", "target": "d_projects_edithub_flutter_app_lib_theme_base", "relation": "defines", "confidence": "EXTRACTED", "confidence_score": 1.0, "source_file": "lib/theme.dart", "source_location": null, "weight": 1.0}, {"source": "d_projects_edithub_flutter_app_lib_theme_dart", "target": "d_projects_edithub_flutter_app_lib_theme_buildtheme", "relation": "defines", "confidence": "EXTRACTED", "confidence_score": 1.0, "source_file": "lib/theme.dart", "source_location": null, "weight": 1.0}, {"source": "d_projects_edithub_flutter_app_lib_theme_dart", "target": "d_projects_edithub_flutter_app_lib_theme_copywith", "relation": "defines", "confidence": "EXTRACTED", "confidence_score": 1.0, "source_file": "lib/theme.dart", "source_location": null, "weight": 1.0}, {"source": "d_projects_edithub_flutter_app_lib_theme_dart", "target": "package_flutter_material_dart", "relation": "imports", "confidence": "EXTRACTED", "confidence_score": 1.0, "source_file": "lib/theme.dart", "source_location": null, "weight": 1.0}, {"source": "d_projects_edithub_flutter_app_lib_theme_dart", "target": "package_google_fonts_google_fonts_dart", "relation": "imports", "confidence": "EXTRACTED", "confidence_score": 1.0, "source_file": "lib/theme.dart", "source_location": null, "weight": 1.0}]}